MultiScaleDeformableAttention.cpython-311-x86_64-linux-gnu.so
functions/__init__.py
functions/ms_deform_attn_func.py
modules/__init__.py
modules/ms_deform_attn.py
ms_deform_attn.libs/libgomp-e985bcbb.so.1.0.0
ms_deform_attn-1.0.1.dist-info/METADATA
ms_deform_attn-1.0.1.dist-info/WHEEL
ms_deform_attn-1.0.1.dist-info/top_level.txt
ms_deform_attn-1.0.1.dist-info/RECORD
ms_deform_attn-1.0.1.dist-info/licenses/LICENSE
