Metadata-Version: 2.4
Name: ms-deform-attn
Version: 1.0.1
Summary: PyTorch Wrapper for CUDA Functions of Multi-Scale Deformable Attention
Author-email: Weijie Su <weijiesu@gmail.com>, Johan Edstedt <johan.edstedt@liu.se>
License: 
Requires-Python: >=3.9
License-File: LICENSE
Requires-Dist: torch
Requires-Dist: numpy
Dynamic: license-file
